setup.py
url2/__init__.py
url2.egg-info/PKG-INFO
url2.egg-info/SOURCES.txt
url2.egg-info/dependency_links.txt
url2.egg-info/top_level.txt